fossyl/__init__.py
fossyl/gridfit.py
fossyl/h5grid.py
fossyl/mcspec.py
fossyl-0.6.2.dist-info/licenses/LICENSE
fossyl-0.6.2.dist-info/METADATA
fossyl-0.6.2.dist-info/WHEEL
fossyl-0.6.2.dist-info/top_level.txt
fossyl-0.6.2.dist-info/RECORD
